astar_pyocean-0.0.4.dist-info/DESCRIPTION.rst
astar_pyocean-0.0.4.dist-info/METADATA
astar_pyocean-0.0.4.dist-info/RECORD
astar_pyocean-0.0.4.dist-info/WHEEL
astar_pyocean-0.0.4.dist-info/metadata.json
astar_pyocean-0.0.4.dist-info/top_level.txt
pyocean/__init__.py
pyocean/disc_burning.py
pyocean/disc_recording.py
pyocean/ODA_system_integrated_service/_ODA_system_integrated_service.py
pyocean/ODA_system_integrated_service/__init__.py
pyocean/base/__init__.py
pyocean/base/_base.py
pyocean/device_basic_info_query/__init__.py
pyocean/device_basic_info_query/_device_basic_info_query.py
pyocean/device_control_basic_operation/__init__.py
pyocean/device_control_basic_operation/_device_control_basic_operation.py
pyocean/file_system_operate/__init__.py
pyocean/file_system_operate/_file_system_operate.py
pyocean/gate_rest_api/__init__.py
pyocean/gate_rest_api/_gate_rest_api.py
pyocean/optical_storage_system_basic_management/__init__.py
pyocean/optical_storage_system_basic_management/_optical_storage_system_basic_management.py
pyocean/system_basic_info_configuration/__init__.py
pyocean/system_basic_info_configuration/_system_basic_info_configuration.py
pyocean/test/__init__.py
pyocean/test/gate_rest_api/__init__.py
pyocean/test/gate_rest_api/_gate_rest_api.py
pyocean/volume_pool_basic_info_management/__init__.py
pyocean/volume_pool_basic_info_management/_volume_pool_basic_info_management.py
