Metadata-Version: 2.0
Name: astar-pyocean
Version: 0.0.4
Summary: toolkit for ocean
Home-page: http://182.61.50.242:10010/astar/pyocean
Author: A.Star
Author-email: astar@snowland.ltd
License: Apache v2.0
Platform: all
Classifier: Operating System :: OS Independent
Classifier: Intended Audience :: Developers
Classifier: Programming Language :: Python
Classifier: Programming Language :: Python :: Implementation
Classifier: Programming Language :: Python :: 3
Classifier: Programming Language :: Python :: 3.6
Classifier: Programming Language :: Python :: 3.7
Classifier: Programming Language :: Python :: 3.8
Classifier: Topic :: Software Development :: Libraries
Requires-Dist: astartool (>=0.0.5)
Requires-Dist: snowland-authsdk
Requires-Dist: requests
